{
    "doc_id": "E2016.790.03_A_02.json", 
    "DCT": "", 
    "category": "", 
    "category_weight": 0, 
    "title": {
        "text": "저녁노을", 
        "NE": ""
    }, 
    "metaInfo": {}, 
    "sentence": [
        {
            "id": 0, 
            "reserve_str": "", 
            "text": "이는 파장이 짧은 푸른색이 산란되어 버리는 반면에 파장이 긴 붉은색의 빛이 산란되지 않고 관측자에게 도달하기 때문이다.", 
            "morp": [
                {"id": 0, "lemma": "이", "type": "NP", "position": 0, "weight": 0.00185676}, 
                {"id": 1, "lemma": "는", "type": "JX", "position": 3, "weight": 0.122593}, 
                {"id": 2, "lemma": "파장", "type": "NNG", "position": 7, "weight": 0.324294}, 
                {"id": 3, "lemma": "이", "type": "JKS", "position": 13, "weight": 0.0360723}, 
                {"id": 4, "lemma": "짧", "type": "VA", "position": 17, "weight": 0.9}, 
                {"id": 5, "lemma": "은", "type": "ETM", "position": 20, "weight": 0.155123}, 
                {"id": 6, "lemma": "푸른색", "type": "NNG", "position": 24, "weight": 0.9}, 
                {"id": 7, "lemma": "이", "type": "JKS", "position": 33, "weight": 0.0360723}, 
                {"id": 8, "lemma": "산란", "type": "NNG", "position": 37, "weight": 0.9}, 
                {"id": 9, "lemma": "되", "type": "XSV", "position": 43, "weight": 0.000224177}, 
                {"id": 10, "lemma": "어", "type": "EC", "position": 46, "weight": 0.361326}, 
                {"id": 11, "lemma": "버리", "type": "VX", "position": 50, "weight": 0.212954}, 
                {"id": 12, "lemma": "는", "type": "ETM", "position": 56, "weight": 0.183966}, 
                {"id": 13, "lemma": "반면", "type": "NNG", "position": 60, "weight": 0.9}, 
                {"id": 14, "lemma": "에", "type": "JKB", "position": 66, "weight": 0.153364}, 
                {"id": 15, "lemma": "파장", "type": "NNG", "position": 70, "weight": 0.207645}, 
                {"id": 16, "lemma": "이", "type": "JKS", "position": 76, "weight": 0.0360723}, 
                {"id": 17, "lemma": "길", "type": "VA", "position": 80, "weight": 0.106026}, 
                {"id": 18, "lemma": "ㄴ", "type": "ETM", "position": 80, "weight": 0.430446}, 
                {"id": 19, "lemma": "붉은색", "type": "NNG", "position": 84, "weight": 0.9}, 
                {"id": 20, "lemma": "의", "type": "JKG", "position": 93, "weight": 0.0694213}, 
                {"id": 21, "lemma": "빛", "type": "NNG", "position": 97, "weight": 0.871257}, 
                {"id": 22, "lemma": "이", "type": "JKS", "position": 100, "weight": 0.0360723}, 
                {"id": 23, "lemma": "산란", "type": "NNG", "position": 104, "weight": 0}, 
                {"id": 24, "lemma": "되", "type": "XSV", "position": 104, "weight": 0}, 
                {"id": 25, "lemma": "지", "type": "EC", "position": 113, "weight": 0.301842}, 
                {"id": 26, "lemma": "않", "type": "VX", "position": 117, "weight": 0.256301}, 
                {"id": 27, "lemma": "고", "type": "EC", "position": 120, "weight": 0.25644}, 
                {"id": 28, "lemma": "관측", "type": "NNG", "position": 124, "weight": 0.9}, 
                {"id": 29, "lemma": "자", "type": "XSN", "position": 130, "weight": 0.00398741}, 
                {"id": 30, "lemma": "에게", "type": "JKB", "position": 133, "weight": 0.121677}, 
                {"id": 31, "lemma": "도달하", "type": "VV", "position": 140, "weight": 0.9}, 
                {"id": 32, "lemma": "기", "type": "ETN", "position": 149, "weight": 0.0380514}, 
                {"id": 33, "lemma": "때문", "type": "NNB", "position": 153, "weight": 0.9}, 
                {"id": 34, "lemma": "이", "type": "VCP", "position": 159, "weight": 0.0607843}, 
                {"id": 35, "lemma": "다", "type": "EF", "position": 162, "weight": 0.353579}, 
                {"id": 36, "lemma": ".", "type": "SF", "position": 165, "weight": 1}
            ], 
            "morp_eval": [], 
            "WSD": [
                {"id": 0, "text": "이", "type": "NP", "scode": "050002", "weight": 0.0172414, "position": 0, "begin": 0, "end": 0}, 
                {"id": 1, "text": "는", "type": "JX", "scode": "000000", "weight": 1, "position": 3, "begin": 1, "end": 1}, 
                {"id": 2, "text": "파장", "type": "NNG", "scode": "020001", "weight": 0.2, "position": 7, "begin": 2, "end": 2}, 
                {"id": 3, "text": "이", "type": "JKS", "scode": "000000", "weight": 1, "position": 13, "begin": 3, "end": 3}, 
                {"id": 4, "text": "짧", "type": "VA", "scode": "000001", "weight": 0.25, "position": 17, "begin": 4, "end": 4}, 
                {"id": 5, "text": "은", "type": "ETM", "scode": "000000", "weight": 1, "position": 20, "begin": 5, "end": 5}, 
                {"id": 6, "text": "푸른색", "type": "NNG", "scode": "000000", "weight": 1, "position": 24, "begin": 6, "end": 6}, 
                {"id": 7, "text": "이", "type": "JKS", "scode": "000000", "weight": 1, "position": 33, "begin": 7, "end": 7}, 
                {"id": 8, "text": "산란", "type": "NNG", "scode": "030000", "weight": 0.25, "position": 37, "begin": 8, "end": 8}, 
                {"id": 9, "text": "되", "type": "XSV", "scode": "050001", "weight": 0.0714286, "position": 43, "begin": 9, "end": 9}, 
                {"id": 10, "text": "어", "type": "EC", "scode": "000000", "weight": 1, "position": 46, "begin": 10, "end": 10}, 
                {"id": 11, "text": "버리", "type": "VX", "scode": "010300", "weight": 0.0714286, "position": 50, "begin": 11, "end": 11}, 
                {"id": 12, "text": "는", "type": "ETM", "scode": "000000", "weight": 1, "position": 56, "begin": 12, "end": 12}, 
                {"id": 13, "text": "반면", "type": "NNG", "scode": "020001", "weight": 0.1, "position": 60, "begin": 13, "end": 13}, 
                {"id": 14, "text": "에", "type": "JKB", "scode": "000000", "weight": 1, "position": 66, "begin": 14, "end": 14}, 
                {"id": 15, "text": "파장", "type": "NNG", "scode": "020001", "weight": 0.2, "position": 70, "begin": 15, "end": 15}, 
                {"id": 16, "text": "이", "type": "JKS", "scode": "000000", "weight": 1, "position": 76, "begin": 16, "end": 16}, 
                {"id": 17, "text": "길", "type": "VA", "scode": "020001", "weight": 0.166667, "position": 80, "begin": 17, "end": 17}, 
                {"id": 18, "text": "ㄴ", "type": "ETM", "scode": "000000", "weight": 1, "position": 80, "begin": 18, "end": 18}, 
                {"id": 19, "text": "붉은색", "type": "NNG", "scode": "000000", "weight": 1, "position": 84, "begin": 19, "end": 19}, 
                {"id": 20, "text": "의", "type": "JKG", "scode": "000000", "weight": 1, "position": 93, "begin": 20, "end": 20}, 
                {"id": 21, "text": "빛", "type": "NNG", "scode": "000001", "weight": 0.166667, "position": 97, "begin": 21, "end": 21}, 
                {"id": 22, "text": "이", "type": "JKS", "scode": "000000", "weight": 1, "position": 100, "begin": 22, "end": 22}, 
                {"id": 23, "text": "산란", "type": "NNG", "scode": "030000", "weight": 0.25, "position": 104, "begin": 23, "end": 23}, 
                {"id": 24, "text": "되", "type": "XSV", "scode": "050001", "weight": 0.0714286, "position": 104, "begin": 24, "end": 24}, 
                {"id": 25, "text": "지", "type": "EC", "scode": "000000", "weight": 1, "position": 113, "begin": 25, "end": 25}, 
                {"id": 26, "text": "않", "type": "VX", "scode": "000200", "weight": 0.333333, "position": 117, "begin": 26, "end": 26}, 
                {"id": 27, "text": "고", "type": "EC", "scode": "000000", "weight": 1, "position": 120, "begin": 27, "end": 27}, 
                {"id": 28, "text": "관측자", "type": "NNG", "scode": "000001", "weight": 0.5, "position": 124, "begin": 28, "end": 29}, 
                {"id": 29, "text": "에게", "type": "JKB", "scode": "000000", "weight": 1, "position": 133, "begin": 30, "end": 30}, 
                {"id": 30, "text": "도달하", "type": "VV", "scode": "010000", "weight": 0.333333, "position": 140, "begin": 31, "end": 31}, 
                {"id": 31, "text": "기", "type": "ETN", "scode": "000000", "weight": 1, "position": 149, "begin": 32, "end": 32}, 
                {"id": 32, "text": "때문", "type": "NNB", "scode": "000000", "weight": 1, "position": 153, "begin": 33, "end": 33}, 
                {"id": 33, "text": "이", "type": "VCP", "scode": "030000", "weight": 0.0172414, "position": 159, "begin": 34, "end": 34}, 
                {"id": 34, "text": "다", "type": "EF", "scode": "000000", "weight": 1, "position": 162, "begin": 35, "end": 35}, 
                {"id": 35, "text": ".", "type": "SF", "scode": "000000", "weight": 1, "position": 165, "begin": 36, "end": 36}
            ], 
            "word": [
                {"id": 0, "text": "이는", "type": "", "begin": 0, "end": 1}, 
                {"id": 1, "text": "파장이", "type": "", "begin": 2, "end": 3}, 
                {"id": 2, "text": "짧은", "type": "", "begin": 4, "end": 5}, 
                {"id": 3, "text": "푸른색이", "type": "", "begin": 6, "end": 7}, 
                {"id": 4, "text": "산란되어", "type": "", "begin": 8, "end": 10}, 
                {"id": 5, "text": "버리는", "type": "", "begin": 11, "end": 12}, 
                {"id": 6, "text": "반면에", "type": "", "begin": 13, "end": 14}, 
                {"id": 7, "text": "파장이", "type": "", "begin": 15, "end": 16}, 
                {"id": 8, "text": "긴", "type": "", "begin": 17, "end": 18}, 
                {"id": 9, "text": "붉은색의", "type": "", "begin": 19, "end": 20}, 
                {"id": 10, "text": "빛이", "type": "", "begin": 21, "end": 22}, 
                {"id": 11, "text": "산란되지", "type": "", "begin": 23, "end": 25}, 
                {"id": 12, "text": "않고", "type": "", "begin": 26, "end": 27}, 
                {"id": 13, "text": "관측자에게", "type": "", "begin": 28, "end": 30}, 
                {"id": 14, "text": "도달하기", "type": "", "begin": 31, "end": 32}, 
                {"id": 15, "text": "때문이다.", "type": "", "begin": 33, "end": 36}
            ], 
            "NE": [
                {"id": 0, "text": "푸른색", "type": "TM_COLOR", "begin": 6, "end": 6, "weight": 0.471174, "common_noun": 0}, 
                {"id": 1, "text": "붉은색", "type": "TM_COLOR", "begin": 19, "end": 19, "weight": 0.619825, "common_noun": 0}
            ], 
            "chunk": [], 
            "dependency": [
                {"id": 0, "text": "이는", "head": 15, "label": "NP_SBJ", "mod": [], "weight": 0.761596}, 
                {"id": 1, "text": "파장이", "head": 2, "label": "NP_SBJ", "mod": [], "weight": 0.707042}, 
                {"id": 2, "text": "짧은", "head": 3, "label": "VP_MOD", "mod": [1], "weight": 0.733362}, 
                {"id": 3, "text": "푸른색이", "head": 4, "label": "NP_SBJ", "mod": [2], "weight": 0.733359}, 
                {"id": 4, "text": "산란되어", "head": 5, "label": "VP", "mod": [3], "weight": 0.806598}, 
                {"id": 5, "text": "버리는", "head": 6, "label": "VP_MOD", "mod": [4], "weight": 0.708595}, 
                {"id": 6, "text": "반면에", "head": 11, "label": "NP_AJT", "mod": [5], "weight": 0.325239}, 
                {"id": 7, "text": "파장이", "head": 8, "label": "NP_SBJ", "mod": [], "weight": 0.394252}, 
                {"id": 8, "text": "긴", "head": 9, "label": "VP_MOD", "mod": [7], "weight": 0.0495778}, 
                {"id": 9, "text": "붉은색의", "head": 10, "label": "NP_MOD", "mod": [8], "weight": 0.642557}, 
                {"id": 10, "text": "빛이", "head": 11, "label": "NP_SBJ", "mod": [9], "weight": 0.807196}, 
                {"id": 11, "text": "산란되지", "head": 12, "label": "VP", "mod": [6, 10], "weight": 0.729398}, 
                {"id": 12, "text": "않고", "head": 14, "label": "VP", "mod": [11], "weight": 0.683595}, 
                {"id": 13, "text": "관측자에게", "head": 14, "label": "NP_AJT", "mod": [], "weight": 0.823489}, 
                {"id": 14, "text": "도달하기", "head": 15, "label": "VP", "mod": [12, 13], "weight": 0.711923}, 
                {"id": 15, "text": "때문이다.", "head": -1, "label": "VNP", "mod": [14, 0], "weight": 0.000136217}
            ], 
            "SRL": [
                {"verb": "짧", "sense": 1, "word_id": 2, "weight": 0.264154, "argument": [
                    {"type": "ARG1", "word_id": 1, "text": "파장이", "weight": 0.264154}
                ]}, 
                {"verb": "산란", "sense": 1, "word_id": 4, "weight": 0.257991, "argument": [
                    {"type": "ARG1", "word_id": 3, "text": "푸른색이", "weight": 0.159431}, 
                    {"type": "AUX", "word_id": 5, "text": "버리는", "weight": 0.356552}
                ]}, 
                {"verb": "길", "sense": 1, "word_id": 8, "weight": 0.227328, "argument": [
                    {"type": "ARG1", "word_id": 7, "text": "파장이", "weight": 0.227328}
                ]}, 
                {"verb": "산란", "sense": 1, "word_id": 11, "weight": 0.280978, "argument": [
                    {"type": "ARG1", "word_id": 10, "text": "빛이", "weight": 0.240768}, 
                    {"type": "ARGM-NEG", "word_id": 12, "text": "않고", "weight": 0.321189}
                ]}, 
                {"verb": "도달", "sense": 1, "word_id": 14, "weight": 0.149672, "argument": [
                    {"type": "ARG2", "word_id": 13, "text": "관측자에게", "weight": 0.149672}, 
                    {"type": "ARG1", "word_id": 10, "text": "빛이", "weight": 1}
                ]}
            ], 
            "relation": [], 
            "SA": [], 
            "ZA": []
        }
    ], 
    "entity": [
        {"id": 0, "type": "", "number": "singular", "gender": "", "person": "", "animacy": "thing", "mention": [
            {"id": 0, "sent_id": 0, "start_eid": 0, "end_eid": 0, "ne_id": -1, "text": "이는", "start_eid_short": 0, "end_eid_short": 0, "text_short": "이는"}
        ]}, 
        {"id": 1, "type": "", "number": "singular", "gender": "", "person": "", "animacy": "thing", "mention": [
            {"id": 1, "sent_id": 0, "start_eid": 1, "end_eid": 6, "ne_id": -1, "text": "파장이 짧은 푸른색이 산란되어 버리는 반면에", "start_eid_short": 6, "end_eid_short": 6, "text_short": "반면에"}
        ]}, 
        {"id": 2, "type": "TM_COLOR", "number": "singular", "gender": "", "person": "", "animacy": "thing", "mention": [
            {"id": 2, "sent_id": 0, "start_eid": 1, "end_eid": 3, "ne_id": 0, "text": "파장이 짧은 푸른색이", "start_eid_short": 3, "end_eid_short": 3, "text_short": "푸른색이"}
        ]}, 
        {"id": 3, "type": "", "number": "singular", "gender": "", "person": "", "animacy": "thing", "mention": [
            {"id": 3, "sent_id": 0, "start_eid": 1, "end_eid": 1, "ne_id": -1, "text": "파장이", "start_eid_short": 1, "end_eid_short": 1, "text_short": "파장이"}, 
            {"id": 6, "sent_id": 0, "start_eid": 7, "end_eid": 7, "ne_id": -1, "text": "파장이", "start_eid_short": 7, "end_eid_short": 7, "text_short": "파장이"}
        ]}, 
        {"id": 4, "type": "TM_COLOR", "number": "singular", "gender": "", "person": "", "animacy": "thing", "mention": [
            {"id": 5, "sent_id": 0, "start_eid": 7, "end_eid": 9, "ne_id": 1, "text": "파장이 긴 붉은색의", "start_eid_short": 9, "end_eid_short": 9, "text_short": "붉은색의"}
        ]}, 
        {"id": 5, "type": "", "number": "singular", "gender": "", "person": "", "animacy": "thing", "mention": [
            {"id": 4, "sent_id": 0, "start_eid": 7, "end_eid": 10, "ne_id": -1, "text": "파장이 긴 붉은색의 빛이", "start_eid_short": 10, "end_eid_short": 10, "text_short": "빛이"}
        ]}, 
        {"id": 6, "type": "", "number": "singular", "gender": "", "person": "", "animacy": "thing", "mention": [
            {"id": 7, "sent_id": 0, "start_eid": 13, "end_eid": 13, "ne_id": -1, "text": "관측자에게", "start_eid_short": 13, "end_eid_short": 13, "text_short": "관측자에게"}
        ]}
    ]
}