<?xml version="1.0" encoding="UTF-8" ?>
<SpaceEvalTaskv1.2.1>
<TEXT><![CDATA[
바기오(Baguio)는 필리핀 루손 섬 중서부 벵겟 군에 있는 소나무로 덮인 해발 1,500m의 구릉지대에 자리한 도시이다. 바기오는 마닐라에서 북쪽으로 130마일 떨어진 산악 지대에 있는 도시이다. 더위를 피해 숨고 싶은 휴양지 해발 고도 1천500m의 고지에 자리 잡은 바기오(Baguio)는 더위를 피할 수 있는 산중 도시이다. 쾌적한 기후로 은퇴 이민 1호지가 된 바기오 지역이다. 필리핀은 열대 지역에 위치하고 있지만, 바기오 지역은 고산 지대로 무덥지 않고 평균 기온이 필리핀의 다른 곳에 비해 8∼10도가 낮다. 마닐라, 일로일로, 세부와 바기오는 이미 많은 한국 유학생들과 어학원들이 주둔되어 있는 곳이다.
]]></TEXT>
<TAGS>
<PLACE id="pl0" start="1" end="4" text="바기오" type="" dimensionality="AREA" form="NOM" domain="" continent="" state="" country="" ctv="" gazref="" latLong="" elevation="" mod="" dcl="FALSE" countable="FALSE" gquant="" scopes="" comment="" />
<PLACE id="pl1" start="14" end="17" text="필리핀" type="" dimensionality="AREA" form="NAM" domain="" continent="" state="" country="" ctv="" gazref="" latLong="" elevation="" mod="" dcl="FALSE" countable="FALSE" gquant="" scopes="" comment="" />
<PLACE id="pl2" start="18" end="22" text="루손 섬" type="" dimensionality="AREA" form="NAM" domain="" continent="" state="" country="" ctv="" gazref="" latLong="" elevation="" mod="" dcl="FALSE" countable="FALSE" gquant="" scopes="" comment="" />
<PLACE id="pl3" start="27" end="31" text="벵겟 군" type="" dimensionality="AREA" form="NAM" domain="" continent="" state="" country="" ctv="" gazref="" latLong="" elevation="" mod="" dcl="FALSE" countable="FALSE" gquant="" scopes="" comment="" />
<PLACE id="pl4" start="55" end="59" text="구릉지대" type="" dimensionality="VOLUME" form="NOM" domain="" continent="" state="" country="" ctv="" gazref="" latLong="" elevation="me0" mod="" dcl="FALSE" countable="FALSE" gquant="" scopes="" comment="" />
<PLACE id="pl5" start="65" end="67" text="도시" type="" dimensionality="AREA" form="NOM" domain="" continent="" state="" country="" ctv="" gazref="" latLong="" elevation="" mod="" dcl="FALSE" countable="TRUE" gquant="" scopes="" comment="" />
<PLACE id="pl6" start="71" end="74" text="바기오" type="" dimensionality="AREA" form="NAM" domain="" continent="" state="" country="" ctv="" gazref="" latLong="" elevation="" mod="" dcl="FALSE" countable="FALSE" gquant="" scopes="" comment="" />
<PLACE id="pl7" start="76" end="79" text="마닐라" type="" dimensionality="AREA" form="NAM" domain="" continent="" state="" country="" ctv="" gazref="" latLong="" elevation="" mod="" dcl="FALSE" countable="FALSE" gquant="" scopes="" comment="" />
<PLACE id="pl9" start="107" end="109" text="도시" type="" dimensionality="AREA" form="NOM" domain="" continent="" state="" country="" ctv="" gazref="" latLong="" elevation="" mod="" dcl="FALSE" countable="TRUE" gquant="" scopes="" comment="" />
<PLACE id="pl11" start="144" end="146" text="고지" type="" dimensionality="VOLUME" form="NOM" domain="" continent="" state="" country="" ctv="" gazref="" latLong="" elevation="" mod="" dcl="FALSE" countable="TRUE" gquant="" scopes="" comment="" />
<PLACE id="pl12" start="154" end="157" text="바기오" type="" dimensionality="AREA" form="NAM" domain="" continent="" state="" country="" ctv="" gazref="" latLong="" elevation="" mod="" dcl="FALSE" countable="FALSE" gquant="" scopes="" comment="" />
<PLACE id="pl13" start="182" end="184" text="도시" type="" dimensionality="AREA" form="NOM" domain="" continent="" state="" country="" ctv="" gazref="" latLong="" elevation="" mod="" dcl="FALSE" countable="TRUE" gquant="" scopes="" comment="" />
<PLACE id="pl14" start="209" end="212" text="바기오" type="" dimensionality="AREA" form="NAM" domain="" continent="" state="" country="" ctv="" gazref="" latLong="" elevation="" mod="" dcl="FALSE" countable="FALSE" gquant="" scopes="" comment="" />
<PLACE id="pl15" start="213" end="215" text="지역" type="" dimensionality="AREA" form="NOM" domain="" continent="" state="" country="" ctv="" gazref="" latLong="" elevation="" mod="" dcl="FALSE" countable="TRUE" gquant="" scopes="" comment="" />
<PLACE id="pl16" start="219" end="222" text="필리핀" type="" dimensionality="AREA" form="NAM" domain="" continent="" state="" country="" ctv="" gazref="" latLong="" elevation="" mod="" dcl="FALSE" countable="FALSE" gquant="" scopes="" comment="" />
<PLACE id="pl21" start="270" end="273" text="필리핀" type="" dimensionality="AREA" form="NAM" domain="" continent="" state="" country="" ctv="" gazref="" latLong="" elevation="" mod="" dcl="FALSE" countable="FALSE" gquant="" scopes="" comment="" />
<PLACE id="pl22" start="278" end="279" text="곳" type="" dimensionality="AREA" form="NOM" domain="" continent="" state="" country="" ctv="" gazref="" latLong="" elevation="" mod="" dcl="FALSE" countable="TRUE" gquant="" scopes="" comment="" />
<PLACE id="pl23" start="295" end="298" text="마닐라" type="" dimensionality="AREA" form="NAM" domain="" continent="" state="" country="" ctv="" gazref="" latLong="" elevation="" mod="" dcl="FALSE" countable="FALSE" gquant="" scopes="" comment="" />
<PLACE id="pl24" start="300" end="304" text="일로일로" type="" dimensionality="AREA" form="NAM" domain="" continent="" state="" country="" ctv="" gazref="" latLong="" elevation="" mod="" dcl="FALSE" countable="FALSE" gquant="" scopes="" comment="" />
<PLACE id="pl25" start="306" end="308" text="세부" type="" dimensionality="AREA" form="NAM" domain="" continent="" state="" country="" ctv="" gazref="" latLong="" elevation="" mod="" dcl="FALSE" countable="FALSE" gquant="" scopes="" comment="" />
<PLACE id="pl26" start="310" end="313" text="바기오" type="" dimensionality="AREA" form="NAM" domain="" continent="" state="" country="" ctv="" gazref="" latLong="" elevation="" mod="" dcl="FALSE" countable="FALSE" gquant="" scopes="" comment="" />
<PLACE id="pl29" start="344" end="345" text="곳" type="" dimensionality="AREA" form="NOM" domain="" continent="" state="" country="" ctv="" gazref="" latLong="" elevation="" mod="" dcl="FALSE" countable="TRUE" gquant="" scopes="" comment="" />
<PLACE id="pl8" start="97" end="102" text="산악 지대" type="" dimensionality="AREA" form="NOM" domain="" continent="" state="" country="" ctv="" gazref="" latLong="" elevation="" mod="" dcl="FALSE" countable="FALSE" gquant="" scopes="" comment="" />
<PLACE id="pl17" start="224" end="229" text="열대 지역" type="" dimensionality="AREA" form="NOM" domain="" continent="" state="" country="" ctv="" gazref="" latLong="" elevation="" mod="" dcl="FALSE" countable="FALSE" gquant="" scopes="" comment="" />
<PLACE id="pl18" start="241" end="247" text="바기오 지역" type="" dimensionality="AREA" form="NAM" domain="" continent="" state="" country="" ctv="" gazref="" latLong="" elevation="" mod="" dcl="FALSE" countable="FALSE" gquant="" scopes="" comment="" />
<PLACE id="pl20" start="249" end="254" text="고산 지대" type="" dimensionality="AREA" form="NOM" domain="" continent="" state="" country="" ctv="" gazref="" latLong="" elevation="" mod="" dcl="FALSE" countable="FALSE" gquant="" scopes="" comment="" />
<SPATIAL_SIGNAL id="s1" start="31" end="32" text="에" cluster="" semantic_type="TOPOLOGICAL" comment="" />
<SPATIAL_SIGNAL id="s2" start="59" end="60" text="에" cluster="" semantic_type="TOPOLOGICAL" comment="" />
<SPATIAL_SIGNAL id="s3" start="82" end="84" text="북쪽" cluster="" semantic_type="DIRECTIONAL" comment="" />
<SPATIAL_SIGNAL id="s4" start="102" end="103" text="에" cluster="" semantic_type="TOPOLOGICAL" comment="" />
<SPATIAL_SIGNAL id="s6" start="146" end="147" text="에" cluster="" semantic_type="TOPOLOGICAL" comment="" />
<SPATIAL_SIGNAL id="s7" start="229" end="230" text="에" cluster="" semantic_type="TOPOLOGICAL" comment="" />
<SPATIAL_SIGNAL id="s0" start="93" end="96" text="떨어진" cluster="" semantic_type="TOPOLOGICAL" comment="" />
<SPATIAL_SIGNAL id="s5" start="23" end="26" text="중서부" cluster="" semantic_type="DIRECTIONAL" comment="" />
<SPATIAL_SIGNAL id="s8" start="273" end="274" text="의" cluster="" semantic_type="TOPOLOGICAL" comment="" />
<MEASURE id="me0" start="47" end="53" text="1,500m" value="1500" unit="m" comment="" />
<MEASURE id="me1" start="87" end="92" text="130마일" value="130" unit="mile" comment="" />
<MEASURE id="me2" start="136" end="142" text="1천500m" value="1500" unit="m" comment="" />
<SENTENCE id="sent0" start="1" end="70" text="바기오(Baguio)는 필리핀 루손 섬 중서부 벵겟 군에 있는 소나무로 덮인 해발 1,500m의 구릉지대에 자리한 도시이다." comment="" />
<SENTENCE id="sent1" start="71" end="112" text="바기오는 마닐라에서 북쪽으로 130마일 떨어진 산악 지대에 있는 도시이다." comment="" />
<SENTENCE id="sent2" start="113" end="187" text="더위를 피해 숨고 싶은 휴양지 해발 고도 1천500m의 고지에 자리 잡은 바기오(Baguio)는 더위를 피할 수 있는 산중 도시이다." comment="" />
<SENTENCE id="sent3" start="188" end="218" text="쾌적한 기후로 은퇴 이민 1호지가 된 바기오 지역이다." comment="" />
<SENTENCE id="sent4" start="219" end="294" text="필리핀은 열대 지역에 위치하고 있지만, 바기오 지역은 고산 지대로 무덥지 않고 평균 기온이 필리핀의 다른 곳에 비해 8∼10도가 낮다." comment="" />
<SENTENCE id="sent5" start="295" end="348" text="마닐라, 일로일로, 세부와 바기오는 이미 많은 한국 유학생들과 어학원들이 주둔되어 있는 곳이다." comment="" />
<QSLINK id="qsl5" fromID="pl4" fromText="구릉지대" toID="pl3" toText="벵겟 군" relType="NTPP" trajector="pl4" landmark="pl3" trigger="s1" comment="" />
<QSLINK id="qsl8" fromID="pl5" fromText="도시" toID="pl4" toText="구릉지대" relType="NTPP" trajector="pl5" landmark="pl4" trigger="s2" comment="" />
<QSLINK id="qsl10" fromID="pl9" fromText="도시" toID="pl8" toText="산악 지대" relType="NTPP" trajector="pl9" landmark="pl8" trigger="s4" comment="" />
<QSLINK id="qsl12" fromID="pl7" fromText="마닐라" toID="pl8" toText="산악 지대" relType="DC" trajector="pl7" landmark="pl8" trigger="s0" comment="" />
<QSLINK id="qsl13" fromID="pl6" fromText="바기오" toID="pl7" toText="마닐라" relType="DC" trajector="pl6" landmark="pl7" trigger="s0" comment="" />
<QSLINK id="qsl15" fromID="pl12" fromText="바기오" toID="pl11" toText="고지" relType="NTPP" trajector="pl12" landmark="pl11" trigger="s6" comment="" />
<QSLINK id="qsl18" fromID="pl16" fromText="필리핀" toID="pl17" toText="열대 지역" relType="NTPP" trajector="pl16" landmark="pl17" trigger="s7" comment="" />
<QSLINK id="qsl0" fromID="pl22" fromText="곳" toID="pl21" toText="필리핀" relType="NTPP" trajector="pl22" landmark="pl21" trigger="s8" comment="" />
<OLINK id="ol3" fromID="pl3" fromText="벵겟 군" toID="pl2" toText="루손 섬" relType="중서" trajector="pl3" landmark="pl2" trigger="s5" frame_type="ABSOLUTE" referencePt="중서" projective="FALSE" comment="" />
<OLINK id="ol4" fromID="pl8" fromText="산악 지대" toID="pl7" toText="마닐라" relType="북" trajector="pl8" landmark="pl7" trigger="s3" frame_type="ABSOLUTE" referencePt="북" projective="FALSE" comment="" />
<MEASURELINK id="ml0" fromID="me0" fromText="1,500m" toID="pl4" toText="구릉지대" trajector="pl4" landmark="pl4" relType="HEIGHT" val="me0" endPoint1="" endPoint2="" comment="" />
<MEASURELINK id="ml2" fromID="pl11" fromText="고지" toID="me2" toText="1천500m" trajector="pl11" landmark="pl11" relType="HEIGHT" val="me2" endPoint1="" endPoint2="" comment="" />
<MEASURELINK id="ml3" fromID="pl8" fromText="산악 지대" toID="pl7" toText="마닐라" trajector="pl8" landmark="pl7" relType="DISTANCE" val="me1" endPoint1="pl8" endPoint2="pl7" comment="" />
<METALINK id="metal0" fromID="pl1" fromText="필리핀" toID="pl2" toText="루손 섬" objectID1="pl2" objectID2="pl1" relType="SUBCOREFERENCE" comment="" />
<METALINK id="metal3" fromID="pl0" fromText="바기오" toID="pl5" toText="도시" objectID1="pl5" objectID2="pl0" relType="COREFERENCE" comment="" />
<METALINK id="metal4" fromID="pl6" fromText="바기오" toID="pl9" toText="도시" objectID1="pl9" objectID2="pl6" relType="COREFERENCE" comment="" />
<METALINK id="metal5" fromID="pl12" fromText="바기오" toID="pl13" toText="도시" objectID1="pl13" objectID2="pl12" relType="COREFERENCE" comment="" />
<METALINK id="metal7" fromID="pl14" fromText="바기오" toID="pl15" toText="지역" objectID1="pl15" objectID2="pl14" relType="COREFERENCE" comment="" />
<METALINK id="metal9" fromID="pl23" fromText="마닐라" toID="pl29" toText="곳" objectID1="pl29" objectID2="pl23" relType="COREFERENCE" comment="" />
<METALINK id="metal10" fromID="pl24" fromText="일로일로" toID="pl29" toText="곳" objectID1="pl29" objectID2="pl24" relType="COREFERENCE" comment="" />
<METALINK id="metal11" fromID="pl25" fromText="세부" toID="pl29" toText="곳" objectID1="pl29" objectID2="pl25" relType="COREFERENCE" comment="" />
<METALINK id="metal12" fromID="pl26" fromText="바기오" toID="pl29" toText="곳" objectID1="pl29" objectID2="pl26" relType="COREFERENCE" comment="" />
</TAGS>
</SpaceEvalTaskv1.2.1>